tasks/__init__.py
tasks/color.py
tasks/commands.py
tasks/events.py
tasks/func.py
tasks/main.py
tasks/model.py
tasks/parse.py
tasks/update.py
tasks/test/__init__.py
tasks/test/test_color.py
tasks/test/test_model.py
tasks/test/test_update.py
tasks-2.8.0.data/scripts/tasks-i3status
tasks-2.8.0.dist-info/METADATA
tasks-2.8.0.dist-info/WHEEL
tasks-2.8.0.dist-info/entry_points.txt
tasks-2.8.0.dist-info/top_level.txt
tasks-2.8.0.dist-info/RECORD
