Metadata-Version: 2.1
Name: tasks
Version: 2.8.0
Summary: A simple personal task queue to track todo items
Home-page: https://github.com/pb-/tasks
Author: Paul Baecher
License: UNKNOWN
Platform: UNKNOWN
Classifier: Programming Language :: Python :: 3
Classifier: License :: OSI Approved :: MIT License
Classifier: Operating System :: OS Independent
